app/__init__.py
app/settings.py
app/application/__init__.py
app/application/services/__init__.py
app/application/services/ask_question_service.py
app/domain/__init__.py
app/domain/exceptions.py
app/domain/interfaces/__init__.py
app/domain/interfaces/answer_gateway.py
app/domain/models/__init__.py
app/domain/models/answer.py
app/infrastructure/__init__.py
app/infrastructure/gateways/__init__.py
app/infrastructure/gateways/http_answer_gateway.py
app/logging/__init__.py
app/logging/gunicorn.py
app/logging/intercept_handler.py
app/presentation/mcp/__init__.py
app/presentation/mcp/app.py
app/presentation/mcp/container.py
app/presentation/mcp/main.py
app/presentation/mcp/prompts.py
app/presentation/mcp/tools.py
no_mcp_server-0.2.2.dist-info/METADATA
no_mcp_server-0.2.2.dist-info/WHEEL
no_mcp_server-0.2.2.dist-info/entry_points.txt
no_mcp_server-0.2.2.dist-info/licenses/LICENSE.md
no_mcp_server-0.2.2.dist-info/RECORD
