Metadata-Version: 2.4
Name: no-mcp-server
Version: 0.2.2
Summary: MCP wrapper for NaaS.
Project-URL: Repository, https://github.com/clafoutis42/no-mcp
Author-email: Charles Labourier <charles@clabouri.dev>
License-File: LICENSE.md
Requires-Python: >=3.11
Requires-Dist: dependency-injector<5,>=4.45.0
Requires-Dist: fastmcp>=2.10.6
Requires-Dist: gunicorn>=23.0.0
Requires-Dist: httpx[http2]<0.29,>=0.28.1
Requires-Dist: loguru<0.8,>=0.7.3
Requires-Dist: mcp>=1.13.0
Requires-Dist: pydantic-settings<3,>=2.7.1
Requires-Dist: pydantic<3,>=2.10.6
Requires-Dist: uvicorn>=0.40.0
